videotimestamps-1.1.0.dist-info/RECORD
videotimestamps-1.1.0.dist-info/WHEEL
videotimestamps-1.1.0.dist-info/entry_points.txt
videotimestamps-1.1.0.dist-info/METADATA
videotimestamps-1.1.0.dist-info/licenses/LICENSE
video_timestamps/rounding_method.py
video_timestamps/__init__.py
video_timestamps/video_timestamps.py
video_timestamps/timestamps_file_parser.py
video_timestamps/fps_timestamps.py
video_timestamps/abc_timestamps.py
video_timestamps/py.typed
video_timestamps/text_file_timestamps.py
video_timestamps/extract_timestamps.py
video_timestamps/time_type.py
video_timestamps/time_unit_converter.py
video_timestamps/video_provider/best_source_video_provider.pyi
video_timestamps/video_provider/abc_video_provider.pyi
video_timestamps/video_provider/__init__.py
video_timestamps/video_provider/ffms2_video_provider.pyi
video_timestamps/video_provider/abc_video_provider.cpython-313-darwin.so
video_timestamps/video_provider/ffms2_video_provider.cpython-313-darwin.so
video_timestamps/video_provider/best_source_video_provider.cpython-313-darwin.so
