Metadata-Version: 2.4
Name: VideoTimestamps
Version: 1.1.0
Summary: Get video timestamps.
Author-Email: moi15moi <moi15moismokerlolilol@gmail.com>
License-Expression: MIT
License-File: LICENSE
Classifier: Development Status :: 5 - Production/Stable
Classifier: Intended Audience :: Developers
Classifier: Programming Language :: Python
Classifier: Programming Language :: Python :: 3
Classifier: Programming Language :: Python :: 3.10
Classifier: Programming Language :: Python :: 3.11
Classifier: Programming Language :: Python :: 3.12
Classifier: Programming Language :: Python :: 3.13
Classifier: Programming Language :: Python :: 3.14
Classifier: Typing :: Typed
Project-URL: Documentation, https://moi15moi.github.io/VideoTimestamps/
Project-URL: Source, https://github.com/moi15moi/VideoTimestamps/
Project-URL: Tracker, https://github.com/moi15moi/VideoTimestamps/issues/
Requires-Python: >=3.10
Provides-Extra: dev
Requires-Dist: coverage>=7.0.0; extra == "dev"
Requires-Dist: mypy>=1.0.0; extra == "dev"
Requires-Dist: pillow>=10.0.0; extra == "dev"
Requires-Dist: pytest>=8.0.0; extra == "dev"
Requires-Dist: ruff>=0.8.4; extra == "dev"
Requires-Dist: mkdocs; extra == "dev"
Requires-Dist: mkdocs-material; extra == "dev"
Requires-Dist: mkdocstrings[python]; extra == "dev"
